CHANGES
LICENSE
MANIFEST.in
README.rst
run.py
setup.py
typetrainer/__init__.py
typetrainer/config.py
typetrainer/generator.py
typetrainer/i18n.py
typetrainer/run.py
typetrainer/stat.py
typetrainer/util.py
typetrainer.egg-info/PKG-INFO
typetrainer.egg-info/SOURCES.txt
typetrainer.egg-info/dependency_links.txt
typetrainer.egg-info/entry_points.txt
typetrainer.egg-info/not-zip-safe
typetrainer.egg-info/top_level.txt
typetrainer/locale/ru/LC_MESSAGES/typetrainer.mo
typetrainer/tutors/__init__.py
typetrainer/tutors/common.py
typetrainer/tutors/en.py
typetrainer/tutors/help.py
typetrainer/tutors/ru.py
typetrainer/tutors/uk.py
typetrainer/ui/__init__.py
typetrainer/ui/kbd.py
typetrainer/ui/main.glade
typetrainer/ui/main.py
typetrainer/ui/stat.glade
typetrainer/ui/stat.py