Metadata-Version: 1.0
Name: typetrainer
Version: 0.5.1
Summary: Typing tutor trainer
Home-page: http://github.com/baverman/typetrainer
Author: Anton Bobrov
Author-email: bobrov@vl.ru
License: UNKNOWN
Platform: UNKNOWN
Classifier: Programming Language :: Python
Classifier: License :: OSI Approved :: MIT License
Classifier: Development Status :: 4 - Beta
Classifier: Environment :: X11 Applications :: GTK
Classifier: Intended Audience :: End Users/Desktop
Classifier: Natural Language :: English
Classifier: Topic :: Education
